README.rst
setup.py
pg_jts/__init__.py
pg_jts/pg_database.py
pg_jts/pg_jts.py
pg_jts/pg_query.py
pg_jts.egg-info/PKG-INFO
pg_jts.egg-info/SOURCES.txt
pg_jts.egg-info/dependency_links.txt
pg_jts.egg-info/top_level.txt