Metadata-Version: 1.1
Name: pg-jts
Version: 0.0.1
Summary: Create JSON-table-schema from a live PostgreSQL database
Home-page: https://github.com/iburadempa/pg_jts
Author: ibu radempa
Author-email: ibu@radempa.de
License: MIT
Keywords: set integer integers range ranges multiple span interval operations
Platform: UNKNOWN
Classifier: Development Status :: 3 - Alpha
Classifier: Intended Audience :: Developers
Classifier: Intended Audience :: Science/Research
Classifier: Topic :: Software Development :: Libraries :: Python Modules
Classifier: Topic :: Utilities
Classifier: License :: OSI Approved :: MIT License
Classifier: Programming Language :: Python :: 3.4
